kli/__init__.py
kli/classes.py
kli/imports.py
kli/main.py
kli/support.py
kli-0.0.15.dist-info/DESCRIPTION.rst
kli-0.0.15.dist-info/METADATA
kli-0.0.15.dist-info/RECORD
kli-0.0.15.dist-info/WHEEL
kli-0.0.15.dist-info/entry_points.txt
kli-0.0.15.dist-info/metadata.json
kli-0.0.15.dist-info/top_level.txt
