Metadata-Version: 2.0
Name: kli
Version: 0.0.15
Summary: UNKNOWN
Home-page: https://github.com/tranquilo12/kli
Author: Shriram Sunder
Author-email: shriram.sunder121091@gmail.com
License: MIT
Keywords: kaggle,cli
Platform: UNKNOWN
Requires-Dist: argcomplete
Requires-Dist: bs4
Requires-Dist: click (>=6)
Requires-Dist: cryptography
Requires-Dist: lxml
Requires-Dist: pprint
Requires-Dist: requests
Requires-Dist: tqdm
